{
  "FilePath": "c:\\Users\\Adan Glez\\OneDrive\\Escritorio\\ProyectoFlotillas\\WebFlotillasTrack\\WebFlotillasTrack\\WebFlotillasTrack.csproj",
  "Configuration": {
    "ConfigurationName": "UnsupportedRazor",
    "LanguageVersion": "1.0",
    "Extensions": [
      {
        "ExtensionName": "UnsupportedRazorExtension"
      }
    ]
  },
  "ProjectWorkspaceState": {
    "TagHelpers": [],
    "CSharpLanguageVersion": 703
  },
  "RootNamespace": null,
  "Documents": [],
  "SerializationFormat": "0.2"
}